assets/__init__.py
liftoff/__init__.py
liftoff/app.py
liftoff/main.py
liftoff/assets/docker-compose.yml
liftoff/assets/nginx.conf
liftoff/assets/vhosts/adminer.conf
liftoff/assets/vhosts/mailhog.conf
liftoff/builders/__init__.py
liftoff/builders/base.py
liftoff/builders/liftoff.py
liftoff/builders/databases/__init__.py
liftoff/builders/databases/base.py
liftoff/builders/databases/mysql.py
liftoff/builders/databases/postgresql.py
liftoff/builders/projects/__init__.py
liftoff/builders/projects/base.py
liftoff/builders/projects/laravel.py
liftoff/builders/projects/php.py
liftoff/controllers/__init__.py
liftoff/controllers/base.py
liftoff/controllers/build.py
liftoff/controllers/init.py
liftoff/controllers/restart.py
liftoff/controllers/start.py
liftoff/controllers/stop.py
liftoff/core/__init__.py
liftoff/core/docker_compose.py
liftoff/core/enums.py
liftoff/core/exc.py
liftoff/core/paths.py
liftoff/core/prompt.py
liftoff/core/vars.py
liftoff/core/version.py
liftoff/ext/__init__.py
liftoff/plugins/__init__.py
liftoff/questionnaires/__init__.py
liftoff/questionnaires/base.py
liftoff/questionnaires/new_project.py
liftoff/questionnaires/projects/__init__.py
liftoff/questionnaires/projects/laravel.py
liftoff/questionnaires/projects/new.py
liftoff/questionnaires/projects/php.py
liftoff/templates/__init__.py
liftoff/templates/command1.jinja2
liftoff/templates/docker-compose.override/php.jinja2
liftoff/templates/vhost/laravel.jinja2
liftoff/templates/vhost/php.jinja2
helium_liftoff-0.0.1.dist-info/LICENSE.md
helium_liftoff-0.0.1.dist-info/METADATA
helium_liftoff-0.0.1.dist-info/WHEEL
helium_liftoff-0.0.1.dist-info/entry_points.txt
helium_liftoff-0.0.1.dist-info/top_level.txt
helium_liftoff-0.0.1.dist-info/RECORD
