Metadata-Version: 2.1
Name: helium-liftoff
Version: 0.0.1
Summary: Command line tools for creating local development projects and resources
Home-page: https://bitbucket.org/teamhelium/com.helium.liftoff.cli/
Author: Helium, LLC
Author-email: developers@heliumservices.com
License: MIT
Platform: UNKNOWN
